streamlit_toggle/__init__.py
streamlit_toggle/frontend/build/asset-manifest.json
streamlit_toggle/frontend/build/bootstrap.min.css
streamlit_toggle/frontend/build/index.html
streamlit_toggle/frontend/build/precache-manifest.f524fe6778645ed0aa310dfb78f19b54.js
streamlit_toggle/frontend/build/service-worker.js
streamlit_toggle/frontend/build/static/js/2.33d556d4.chunk.js
streamlit_toggle/frontend/build/static/js/2.33d556d4.chunk.js.LICENSE.txt
streamlit_toggle/frontend/build/static/js/2.33d556d4.chunk.js.map
streamlit_toggle/frontend/build/static/js/main.508efdfd.chunk.js
streamlit_toggle/frontend/build/static/js/main.508efdfd.chunk.js.map
streamlit_toggle/frontend/build/static/js/runtime-main.fd5c39a2.js
streamlit_toggle/frontend/build/static/js/runtime-main.fd5c39a2.js.map
streamlit_toggle_switch-1.0.2.dist-info/LICENSE
streamlit_toggle_switch-1.0.2.dist-info/METADATA
streamlit_toggle_switch-1.0.2.dist-info/WHEEL
streamlit_toggle_switch-1.0.2.dist-info/top_level.txt
streamlit_toggle_switch-1.0.2.dist-info/RECORD
