Metadata-Version: 2.1
Name: streamlit_toggle_switch
Version: 1.0.2
Summary: Creates a customizable toggle
Home-page: https://github.com/sqlinsights/streamlit-toggle-switch
Author: Carlos D. Serrano
Author-email: sqlinsights@gmail.com
License: UNKNOWN
Platform: UNKNOWN
Requires-Python: >=3.6
License-File: LICENSE
